README.md
setup.cfg
setup.py
my_first_distributions_15/Binomialdistribution.py
my_first_distributions_15/Gaussiandistribution.py
my_first_distributions_15/Generaldistribution.py
my_first_distributions_15/__init__.py
my_first_distributions_15.egg-info/PKG-INFO
my_first_distributions_15.egg-info/SOURCES.txt
my_first_distributions_15.egg-info/dependency_links.txt
my_first_distributions_15.egg-info/not-zip-safe
my_first_distributions_15.egg-info/top_level.txt