Metadata-Version: 1.0
Name: my-first-distributions-15
Version: 0.1
Summary: Gaussian and Binomial distributions
Home-page: UNKNOWN
Author: UNKNOWN
Author-email: UNKNOWN
License: UNKNOWN
Platform: UNKNOWN
